tensorflow_federated/__init__.py
tensorflow_federated/version.py
tensorflow_federated/experimental/__init__.py
tensorflow_federated/experimental/python/__init__.py
tensorflow_federated/experimental/python/core/__init__.py
tensorflow_federated/experimental/python/core/api/__init__.py
tensorflow_federated/experimental/python/core/api/computations.py
tensorflow_federated/experimental/python/core/impl/__init__.py
tensorflow_federated/experimental/python/core/impl/jax_context/__init__.py
tensorflow_federated/experimental/python/core/impl/jax_context/jax_computation_context.py
tensorflow_federated/experimental/python/core/impl/jax_context/jax_serialization.py
tensorflow_federated/experimental/python/core/impl/wrappers/__init__.py
tensorflow_federated/experimental/python/core/impl/wrappers/computation_wrapper_instances.py
tensorflow_federated/experimental/python/learning/__init__.py
tensorflow_federated/experimental/python/learning/jax_components.py
tensorflow_federated/proto/__init__.py
tensorflow_federated/proto/v0/__init__.py
tensorflow_federated/proto/v0/computation_pb2.py
tensorflow_federated/proto/v0/executor_pb2.py
tensorflow_federated/proto/v0/executor_pb2_grpc.py
tensorflow_federated/python/__init__.py
tensorflow_federated/python/aggregators/__init__.py
tensorflow_federated/python/aggregators/concat.py
tensorflow_federated/python/aggregators/differential_privacy.py
tensorflow_federated/python/aggregators/encoded.py
tensorflow_federated/python/aggregators/factory.py
tensorflow_federated/python/aggregators/hadamard.py
tensorflow_federated/python/aggregators/mean.py
tensorflow_federated/python/aggregators/measurements.py
tensorflow_federated/python/aggregators/primitives.py
tensorflow_federated/python/aggregators/quantile_estimation.py
tensorflow_federated/python/aggregators/robust.py
tensorflow_federated/python/aggregators/rotation.py
tensorflow_federated/python/aggregators/sampling.py
tensorflow_federated/python/aggregators/secure.py
tensorflow_federated_nightly-0.19.0.dev20220218.dist-info/METADATA
tensorflow_federated_nightly-0.19.0.dev20220218.dist-info/WHEEL
tensorflow_federated_nightly-0.19.0.dev20220218.dist-info/top_level.txt
tensorflow_federated_nightly-0.19.0.dev20220218.dist-info/RECORD
