Metadata-Version: 2.1
Name: tensorflow-federated-nightly
Version: 0.19.0.dev20220218
Summary: TensorFlow Federated is an open-source federated learning framework.
Home-page: http://tensorflow.org/federated
Download-URL: https://github.com/tensorflow/federated/tags
Author: Google Inc.
Author-email: packages@tensorflow.org
License: Apache 2.0
Keywords: tensorflow federated machine learning
Platform: UNKNOWN
Classifier: Development Status :: 5 - Production/Stable
Classifier: Intended Audience :: Developers
Classifier: Intended Audience :: Education
Classifier: Intended Audience :: Science/Research
Classifier: License :: OSI Approved :: Apache Software License
Classifier: Operating System :: POSIX :: Linux
Classifier: Programming Language :: Python :: 3
Classifier: Programming Language :: Python :: 3.7
Classifier: Programming Language :: Python :: 3.8
Classifier: Programming Language :: Python :: 3.9
Classifier: Programming Language :: Python :: 3 :: Only
Classifier: Topic :: Scientific/Engineering
Classifier: Topic :: Scientific/Engineering :: Artificial Intelligence
Classifier: Topic :: Scientific/Engineering :: Mathematics
Classifier: Topic :: Software Development
Classifier: Topic :: Software Development :: Libraries
Classifier: Topic :: Software Development :: Libraries :: Python Modules
Requires-Dist: absl-py (~=1.0.0)
Requires-Dist: attrs (~=21.2.0)
Requires-Dist: cachetools (~=3.1.1)
Requires-Dist: dm-tree (~=0.1.1)
Requires-Dist: farmhashpy (~=0.4.0)
Requires-Dist: grpcio (~=1.37.0)
Requires-Dist: jax (~=0.2.27)
Requires-Dist: jaxlib (~=0.1.76)
Requires-Dist: numpy (~=1.21.4)
Requires-Dist: portpicker (~=1.3.1)
Requires-Dist: semantic-version (~=2.8.5)
Requires-Dist: tensorflow-model-optimization (~=0.7.1)
Requires-Dist: tensorflow-privacy (~=0.7.3)
Requires-Dist: tf-nightly
Requires-Dist: tqdm (~=4.28.1)
